{
  "version": "5",
  "dialect": "mysql",
  "id": "0041900e-149e-4cfc-b78f-1aa0c1e102eb",
  "prevId": "00000000-0000-0000-0000-000000000000",
  "tables": {
    "book_listings": {
      "name": "book_listings",
      "columns": {
        "id": {
          "name": "id",
          "type": "int",
          "primaryKey": false,
          "notNull": true,
          "autoincrement": true
        },
        "seller_id": {
          "name": "seller_id",
          "type": "varchar(36)",
          "primaryKey": false,
          "notNull": true,
          "autoincrement": false
        },
        "title": {
          "name": "title",
          "type": "varchar(500)",
          "primaryKey": false,
          "notNull": true,
          "autoincrement": false
        },
        "isbn": {
          "name": "isbn",
          "type": "varchar(20)",
          "primaryKey": false,
          "notNull": false,
          "autoincrement": false
        },
        "local_code": {
          "name": "local_code",
          "type": "varchar(50)",
          "primaryKey": false,
          "notNull": false,
          "autoincrement": false
        },
        "publisher": {
          "name": "publisher",
          "type": "varchar(255)",
          "primaryKey": false,
          "notNull": false,
          "autoincrement": false
        },
        "author": {
          "name": "author",
          "type": "varchar(255)",
          "primaryKey": false,
          "notNull": false,
          "autoincrement": false
        },
        "edition": {
          "name": "edition",
          "type": "varchar(50)",
          "primaryKey": false,
          "notNull": false,
          "autoincrement": false
        },
        "publication_year": {
          "name": "publication_year",
          "type": "int",
          "primaryKey": false,
          "notNull": false,
          "autoincrement": false
        },
        "language": {
          "name": "language",
          "type": "varchar(50)",
          "primaryKey": false,
          "notNull": false,
          "autoincrement": false,
          "default": "'English'"
        },
        "binding_type": {
          "name": "binding_type",
          "type": "varchar(50)",
          "primaryKey": false,
          "notNull": false,
          "autoincrement": false
        },
        "book_type": {
          "name": "book_type",
          "type": "varchar(50)",
          "primaryKey": false,
          "notNull": false,
          "autoincrement": false,
          "default": "'Hardcopy'"
        },
        "number_of_pages": {
          "name": "number_of_pages",
          "type": "int",
          "primaryKey": false,
          "notNull": false,
          "autoincrement": false
        },
        "class_grade": {
          "name": "class_grade",
          "type": "varchar(50)",
          "primaryKey": false,
          "notNull": false,
          "autoincrement": false
        },
        "subject": {
          "name": "subject",
          "type": "varchar(100)",
          "primaryKey": false,
          "notNull": false,
          "autoincrement": false
        },
        "curriculum": {
          "name": "curriculum",
          "type": "varchar(50)",
          "primaryKey": false,
          "notNull": false,
          "autoincrement": false
        },
        "age_range": {
          "name": "age_range",
          "type": "varchar(50)",
          "primaryKey": false,
          "notNull": false,
          "autoincrement": false
        },
        "region": {
          "name": "region",
          "type": "varchar(50)",
          "primaryKey": false,
          "notNull": false,
          "autoincrement": false,
          "default": "'Kenyan'"
        },
        "term": {
          "name": "term",
          "type": "varchar(20)",
          "primaryKey": false,
          "notNull": false,
          "autoincrement": false
        },
        "condition": {
          "name": "condition",
          "type": "varchar(20)",
          "primaryKey": false,
          "notNull": true,
          "autoincrement": false
        },
        "condition_notes": {
          "name": "condition_notes",
          "type": "text",
          "primaryKey": false,
          "notNull": false,
          "autoincrement": false
        },
        "price": {
          "name": "price",
          "type": "decimal(10,2)",
          "primaryKey": false,
          "notNull": true,
          "autoincrement": false
        },
        "original_retail_price": {
          "name": "original_retail_price",
          "type": "decimal(10,2)",
          "primaryKey": false,
          "notNull": false,
          "autoincrement": false
        },
        "negotiable": {
          "name": "negotiable",
          "type": "boolean",
          "primaryKey": false,
          "notNull": false,
          "autoincrement": false,
          "default": true
        },
        "description": {
          "name": "description",
          "type": "text",
          "primaryKey": false,
          "notNull": false,
          "autoincrement": false
        },
        "quantity_available": {
          "name": "quantity_available",
          "type": "int",
          "primaryKey": false,
          "notNull": false,
          "autoincrement": false,
          "default": 1
        },
        "listing_status": {
          "name": "listing_status",
          "type": "varchar(20)",
          "primaryKey": false,
          "notNull": false,
          "autoincrement": false,
          "default": "'active'"
        },
        "listing_type": {
          "name": "listing_type",
          "type": "varchar(20)",
          "primaryKey": false,
          "notNull": false,
          "autoincrement": false,
          "default": "'sell'"
        },
        "willing_to_swap_for": {
          "name": "willing_to_swap_for",
          "type": "text",
          "primaryKey": false,
          "notNull": false,
          "autoincrement": false
        },
        "primary_photo_url": {
          "name": "primary_photo_url",
          "type": "text",
          "primaryKey": false,
          "notNull": false,
          "autoincrement": false
        },
        "views_count": {
          "name": "views_count",
          "type": "int",
          "primaryKey": false,
          "notNull": false,
          "autoincrement": false,
          "default": 0
        },
        "favorites_count": {
          "name": "favorites_count",
          "type": "int",
          "primaryKey": false,
          "notNull": false,
          "autoincrement": false,
          "default": 0
        },
        "created_at": {
          "name": "created_at",
          "type": "timestamp",
          "primaryKey": false,
          "notNull": true,
          "autoincrement": false,
          "default": "(now())"
        },
        "updated_at": {
          "name": "updated_at",
          "type": "timestamp",
          "primaryKey": false,
          "notNull": true,
          "autoincrement": false,
          "default": "(now())"
        },
        "sold_at": {
          "name": "sold_at",
          "type": "datetime",
          "primaryKey": false,
          "notNull": false,
          "autoincrement": false
        },
        "expires_at": {
          "name": "expires_at",
          "type": "datetime",
          "primaryKey": false,
          "notNull": false,
          "autoincrement": false
        }
      },
      "indexes": {},
      "foreignKeys": {
        "book_listings_seller_id_users_id_fk": {
          "name": "book_listings_seller_id_users_id_fk",
          "tableFrom": "book_listings",
          "tableTo": "users",
          "columnsFrom": [
            "seller_id"
          ],
          "columnsTo": [
            "id"
          ],
          "onDelete": "cascade",
          "onUpdate": "no action"
        }
      },
      "compositePrimaryKeys": {
        "book_listings_id": {
          "name": "book_listings_id",
          "columns": [
            "id"
          ]
        }
      },
      "uniqueConstraints": {},
      "checkConstraint": {}
    },
    "book_photos": {
      "name": "book_photos",
      "columns": {
        "id": {
          "name": "id",
          "type": "int",
          "primaryKey": false,
          "notNull": true,
          "autoincrement": true
        },
        "listing_id": {
          "name": "listing_id",
          "type": "int",
          "primaryKey": false,
          "notNull": true,
          "autoincrement": false
        },
        "photo_url": {
          "name": "photo_url",
          "type": "text",
          "primaryKey": false,
          "notNull": true,
          "autoincrement": false
        },
        "photo_type": {
          "name": "photo_type",
          "type": "varchar(50)",
          "primaryKey": false,
          "notNull": false,
          "autoincrement": false
        },
        "display_order": {
          "name": "display_order",
          "type": "int",
          "primaryKey": false,
          "notNull": false,
          "autoincrement": false,
          "default": 0
        },
        "uploaded_at": {
          "name": "uploaded_at",
          "type": "timestamp",
          "primaryKey": false,
          "notNull": false,
          "autoincrement": false,
          "default": "(now())"
        }
      },
      "indexes": {},
      "foreignKeys": {
        "book_photos_listing_id_book_listings_id_fk": {
          "name": "book_photos_listing_id_book_listings_id_fk",
          "tableFrom": "book_photos",
          "tableTo": "book_listings",
          "columnsFrom": [
            "listing_id"
          ],
          "columnsTo": [
            "id"
          ],
          "onDelete": "cascade",
          "onUpdate": "no action"
        }
      },
      "compositePrimaryKeys": {
        "book_photos_id": {
          "name": "book_photos_id",
          "columns": [
            "id"
          ]
        }
      },
      "uniqueConstraints": {},
      "checkConstraint": {}
    },
    "class_grades": {
      "name": "class_grades",
      "columns": {
        "id": {
          "name": "id",
          "type": "int",
          "primaryKey": false,
          "notNull": true,
          "autoincrement": true
        },
        "name": {
          "name": "name",
          "type": "varchar(50)",
          "primaryKey": false,
          "notNull": true,
          "autoincrement": false
        },
        "curriculum": {
          "name": "curriculum",
          "type": "varchar(50)",
          "primaryKey": false,
          "notNull": false,
          "autoincrement": false
        },
        "sort_order": {
          "name": "sort_order",
          "type": "int",
          "primaryKey": false,
          "notNull": false,
          "autoincrement": false
        },
        "age_range": {
          "name": "age_range",
          "type": "varchar(50)",
          "primaryKey": false,
          "notNull": false,
          "autoincrement": false
        }
      },
      "indexes": {},
      "foreignKeys": {},
      "compositePrimaryKeys": {
        "class_grades_id": {
          "name": "class_grades_id",
          "columns": [
            "id"
          ]
        }
      },
      "uniqueConstraints": {
        "class_grades_name_unique": {
          "name": "class_grades_name_unique",
          "columns": [
            "name"
          ]
        }
      },
      "checkConstraint": {}
    },
    "escrow_accounts": {
      "name": "escrow_accounts",
      "columns": {
        "id": {
          "name": "id",
          "type": "int",
          "primaryKey": false,
          "notNull": true,
          "autoincrement": true
        },
        "book_listing_id": {
          "name": "book_listing_id",
          "type": "int",
          "primaryKey": false,
          "notNull": true,
          "autoincrement": false
        },
        "buyer_id": {
          "name": "buyer_id",
          "type": "varchar(36)",
          "primaryKey": false,
          "notNull": true,
          "autoincrement": false
        },
        "seller_id": {
          "name": "seller_id",
          "type": "varchar(36)",
          "primaryKey": false,
          "notNull": true,
          "autoincrement": false
        },
        "amount": {
          "name": "amount",
          "type": "decimal(10,2)",
          "primaryKey": false,
          "notNull": true,
          "autoincrement": false
        },
        "currency": {
          "name": "currency",
          "type": "varchar(10)",
          "primaryKey": false,
          "notNull": true,
          "autoincrement": false,
          "default": "'KES'"
        },
        "platform_fee": {
          "name": "platform_fee",
          "type": "decimal(10,2)",
          "primaryKey": false,
          "notNull": true,
          "autoincrement": false,
          "default": "'0.00'"
        },
        "status": {
          "name": "status",
          "type": "varchar(20)",
          "primaryKey": false,
          "notNull": true,
          "autoincrement": false,
          "default": "'pending'"
        },
        "hold_period_days": {
          "name": "hold_period_days",
          "type": "int",
          "primaryKey": false,
          "notNull": true,
          "autoincrement": false,
          "default": 7
        },
        "release_at": {
          "name": "release_at",
          "type": "timestamp",
          "primaryKey": false,
          "notNull": true,
          "autoincrement": false
        },
        "released_at": {
          "name": "released_at",
          "type": "timestamp",
          "primaryKey": false,
          "notNull": false,
          "autoincrement": false
        },
        "refunded_at": {
          "name": "refunded_at",
          "type": "timestamp",
          "primaryKey": false,
          "notNull": false,
          "autoincrement": false
        },
        "dispute_reason": {
          "name": "dispute_reason",
          "type": "text",
          "primaryKey": false,
          "notNull": false,
          "autoincrement": false
        },
        "dispute_resolved_at": {
          "name": "dispute_resolved_at",
          "type": "timestamp",
          "primaryKey": false,
          "notNull": false,
          "autoincrement": false
        },
        "notes": {
          "name": "notes",
          "type": "text",
          "primaryKey": false,
          "notNull": false,
          "autoincrement": false
        },
        "created_at": {
          "name": "created_at",
          "type": "timestamp",
          "primaryKey": false,
          "notNull": true,
          "autoincrement": false,
          "default": "(now())"
        },
        "updated_at": {
          "name": "updated_at",
          "type": "timestamp",
          "primaryKey": false,
          "notNull": true,
          "autoincrement": false,
          "default": "(now())"
        }
      },
      "indexes": {},
      "foreignKeys": {
        "escrow_accounts_book_listing_id_book_listings_id_fk": {
          "name": "escrow_accounts_book_listing_id_book_listings_id_fk",
          "tableFrom": "escrow_accounts",
          "tableTo": "book_listings",
          "columnsFrom": [
            "book_listing_id"
          ],
          "columnsTo": [
            "id"
          ],
          "onDelete": "cascade",
          "onUpdate": "no action"
        },
        "escrow_accounts_buyer_id_users_id_fk": {
          "name": "escrow_accounts_buyer_id_users_id_fk",
          "tableFrom": "escrow_accounts",
          "tableTo": "users",
          "columnsFrom": [
            "buyer_id"
          ],
          "columnsTo": [
            "id"
          ],
          "onDelete": "cascade",
          "onUpdate": "no action"
        },
        "escrow_accounts_seller_id_users_id_fk": {
          "name": "escrow_accounts_seller_id_users_id_fk",
          "tableFrom": "escrow_accounts",
          "tableTo": "users",
          "columnsFrom": [
            "seller_id"
          ],
          "columnsTo": [
            "id"
          ],
          "onDelete": "cascade",
          "onUpdate": "no action"
        }
      },
      "compositePrimaryKeys": {
        "escrow_accounts_id": {
          "name": "escrow_accounts_id",
          "columns": [
            "id"
          ]
        }
      },
      "uniqueConstraints": {},
      "checkConstraint": {}
    },
    "favorites": {
      "name": "favorites",
      "columns": {
        "id": {
          "name": "id",
          "type": "int",
          "primaryKey": false,
          "notNull": true,
          "autoincrement": true
        },
        "user_id": {
          "name": "user_id",
          "type": "varchar(36)",
          "primaryKey": false,
          "notNull": true,
          "autoincrement": false
        },
        "listing_id": {
          "name": "listing_id",
          "type": "int",
          "primaryKey": false,
          "notNull": true,
          "autoincrement": false
        },
        "added_at": {
          "name": "added_at",
          "type": "timestamp",
          "primaryKey": false,
          "notNull": false,
          "autoincrement": false,
          "default": "(now())"
        }
      },
      "indexes": {
        "idx_favorites_user_id": {
          "name": "idx_favorites_user_id",
          "columns": [
            "user_id"
          ],
          "isUnique": false
        },
        "idx_favorites_listing_id": {
          "name": "idx_favorites_listing_id",
          "columns": [
            "listing_id"
          ],
          "isUnique": false
        }
      },
      "foreignKeys": {
        "favorites_user_id_users_id_fk": {
          "name": "favorites_user_id_users_id_fk",
          "tableFrom": "favorites",
          "tableTo": "users",
          "columnsFrom": [
            "user_id"
          ],
          "columnsTo": [
            "id"
          ],
          "onDelete": "cascade",
          "onUpdate": "no action"
        },
        "favorites_listing_id_book_listings_id_fk": {
          "name": "favorites_listing_id_book_listings_id_fk",
          "tableFrom": "favorites",
          "tableTo": "book_listings",
          "columnsFrom": [
            "listing_id"
          ],
          "columnsTo": [
            "id"
          ],
          "onDelete": "cascade",
          "onUpdate": "no action"
        }
      },
      "compositePrimaryKeys": {
        "favorites_id": {
          "name": "favorites_id",
          "columns": [
            "id"
          ]
        }
      },
      "uniqueConstraints": {},
      "checkConstraint": {}
    },
    "notifications": {
      "name": "notifications",
      "columns": {
        "id": {
          "name": "id",
          "type": "int",
          "primaryKey": false,
          "notNull": true,
          "autoincrement": true
        },
        "user_id": {
          "name": "user_id",
          "type": "varchar(36)",
          "primaryKey": false,
          "notNull": true,
          "autoincrement": false
        },
        "type": {
          "name": "type",
          "type": "varchar(50)",
          "primaryKey": false,
          "notNull": true,
          "autoincrement": false
        },
        "title": {
          "name": "title",
          "type": "varchar(255)",
          "primaryKey": false,
          "notNull": true,
          "autoincrement": false
        },
        "message": {
          "name": "message",
          "type": "text",
          "primaryKey": false,
          "notNull": true,
          "autoincrement": false
        },
        "related_swap_request_id": {
          "name": "related_swap_request_id",
          "type": "int",
          "primaryKey": false,
          "notNull": false,
          "autoincrement": false
        },
        "related_book_listing_id": {
          "name": "related_book_listing_id",
          "type": "int",
          "primaryKey": false,
          "notNull": false,
          "autoincrement": false
        },
        "related_order_id": {
          "name": "related_order_id",
          "type": "int",
          "primaryKey": false,
          "notNull": false,
          "autoincrement": false
        },
        "action_url": {
          "name": "action_url",
          "type": "varchar(500)",
          "primaryKey": false,
          "notNull": false,
          "autoincrement": false
        },
        "is_read": {
          "name": "is_read",
          "type": "boolean",
          "primaryKey": false,
          "notNull": true,
          "autoincrement": false,
          "default": false
        },
        "read_at": {
          "name": "read_at",
          "type": "timestamp",
          "primaryKey": false,
          "notNull": false,
          "autoincrement": false
        },
        "created_at": {
          "name": "created_at",
          "type": "timestamp",
          "primaryKey": false,
          "notNull": true,
          "autoincrement": false,
          "default": "(now())"
        }
      },
      "indexes": {
        "idx_notifications_user_id": {
          "name": "idx_notifications_user_id",
          "columns": [
            "user_id"
          ],
          "isUnique": false
        },
        "idx_notifications_is_read": {
          "name": "idx_notifications_is_read",
          "columns": [
            "is_read"
          ],
          "isUnique": false
        },
        "idx_notifications_type": {
          "name": "idx_notifications_type",
          "columns": [
            "type"
          ],
          "isUnique": false
        }
      },
      "foreignKeys": {
        "notifications_user_id_users_id_fk": {
          "name": "notifications_user_id_users_id_fk",
          "tableFrom": "notifications",
          "tableTo": "users",
          "columnsFrom": [
            "user_id"
          ],
          "columnsTo": [
            "id"
          ],
          "onDelete": "cascade",
          "onUpdate": "no action"
        },
        "notifications_related_swap_request_id_swap_requests_id_fk": {
          "name": "notifications_related_swap_request_id_swap_requests_id_fk",
          "tableFrom": "notifications",
          "tableTo": "swap_requests",
          "columnsFrom": [
            "related_swap_request_id"
          ],
          "columnsTo": [
            "id"
          ],
          "onDelete": "cascade",
          "onUpdate": "no action"
        },
        "notifications_related_book_listing_id_book_listings_id_fk": {
          "name": "notifications_related_book_listing_id_book_listings_id_fk",
          "tableFrom": "notifications",
          "tableTo": "book_listings",
          "columnsFrom": [
            "related_book_listing_id"
          ],
          "columnsTo": [
            "id"
          ],
          "onDelete": "cascade",
          "onUpdate": "no action"
        },
        "notifications_related_order_id_orders_id_fk": {
          "name": "notifications_related_order_id_orders_id_fk",
          "tableFrom": "notifications",
          "tableTo": "orders",
          "columnsFrom": [
            "related_order_id"
          ],
          "columnsTo": [
            "id"
          ],
          "onDelete": "cascade",
          "onUpdate": "no action"
        }
      },
      "compositePrimaryKeys": {
        "notifications_id": {
          "name": "notifications_id",
          "columns": [
            "id"
          ]
        }
      },
      "uniqueConstraints": {},
      "checkConstraint": {}
    },
    "orders": {
      "name": "orders",
      "columns": {
        "id": {
          "name": "id",
          "type": "int",
          "primaryKey": false,
          "notNull": true,
          "autoincrement": true
        },
        "order_number": {
          "name": "order_number",
          "type": "varchar(50)",
          "primaryKey": false,
          "notNull": true,
          "autoincrement": false
        },
        "buyer_id": {
          "name": "buyer_id",
          "type": "varchar(36)",
          "primaryKey": false,
          "notNull": true,
          "autoincrement": false
        },
        "seller_id": {
          "name": "seller_id",
          "type": "varchar(36)",
          "primaryKey": false,
          "notNull": true,
          "autoincrement": false
        },
        "book_listing_id": {
          "name": "book_listing_id",
          "type": "int",
          "primaryKey": false,
          "notNull": true,
          "autoincrement": false
        },
        "quantity": {
          "name": "quantity",
          "type": "int",
          "primaryKey": false,
          "notNull": true,
          "autoincrement": false,
          "default": 1
        },
        "total_amount": {
          "name": "total_amount",
          "type": "decimal(10,2)",
          "primaryKey": false,
          "notNull": true,
          "autoincrement": false
        },
        "platform_fee": {
          "name": "platform_fee",
          "type": "decimal(10,2)",
          "primaryKey": false,
          "notNull": true,
          "autoincrement": false,
          "default": "'0.00'"
        },
        "seller_amount": {
          "name": "seller_amount",
          "type": "decimal(10,2)",
          "primaryKey": false,
          "notNull": true,
          "autoincrement": false
        },
        "status": {
          "name": "status",
          "type": "varchar(20)",
          "primaryKey": false,
          "notNull": true,
          "autoincrement": false,
          "default": "'pending'"
        },
        "escrow_id": {
          "name": "escrow_id",
          "type": "int",
          "primaryKey": false,
          "notNull": false,
          "autoincrement": false
        },
        "delivery_method": {
          "name": "delivery_method",
          "type": "varchar(50)",
          "primaryKey": false,
          "notNull": false,
          "autoincrement": false
        },
        "delivery_address": {
          "name": "delivery_address",
          "type": "text",
          "primaryKey": false,
          "notNull": false,
          "autoincrement": false
        },
        "tracking_number": {
          "name": "tracking_number",
          "type": "varchar(100)",
          "primaryKey": false,
          "notNull": false,
          "autoincrement": false
        },
        "paid_at": {
          "name": "paid_at",
          "type": "timestamp",
          "primaryKey": false,
          "notNull": false,
          "autoincrement": false
        },
        "confirmed_at": {
          "name": "confirmed_at",
          "type": "timestamp",
          "primaryKey": false,
          "notNull": false,
          "autoincrement": false
        },
        "delivered_at": {
          "name": "delivered_at",
          "type": "timestamp",
          "primaryKey": false,
          "notNull": false,
          "autoincrement": false
        },
        "completed_at": {
          "name": "completed_at",
          "type": "timestamp",
          "primaryKey": false,
          "notNull": false,
          "autoincrement": false
        },
        "cancelled_at": {
          "name": "cancelled_at",
          "type": "timestamp",
          "primaryKey": false,
          "notNull": false,
          "autoincrement": false
        },
        "buyer_notes": {
          "name": "buyer_notes",
          "type": "text",
          "primaryKey": false,
          "notNull": false,
          "autoincrement": false
        },
        "seller_notes": {
          "name": "seller_notes",
          "type": "text",
          "primaryKey": false,
          "notNull": false,
          "autoincrement": false
        },
        "cancellation_reason": {
          "name": "cancellation_reason",
          "type": "text",
          "primaryKey": false,
          "notNull": false,
          "autoincrement": false
        },
        "created_at": {
          "name": "created_at",
          "type": "timestamp",
          "primaryKey": false,
          "notNull": true,
          "autoincrement": false,
          "default": "(now())"
        },
        "updated_at": {
          "name": "updated_at",
          "type": "timestamp",
          "primaryKey": false,
          "notNull": true,
          "autoincrement": false,
          "default": "(now())"
        }
      },
      "indexes": {},
      "foreignKeys": {
        "orders_buyer_id_users_id_fk": {
          "name": "orders_buyer_id_users_id_fk",
          "tableFrom": "orders",
          "tableTo": "users",
          "columnsFrom": [
            "buyer_id"
          ],
          "columnsTo": [
            "id"
          ],
          "onDelete": "cascade",
          "onUpdate": "no action"
        },
        "orders_seller_id_users_id_fk": {
          "name": "orders_seller_id_users_id_fk",
          "tableFrom": "orders",
          "tableTo": "users",
          "columnsFrom": [
            "seller_id"
          ],
          "columnsTo": [
            "id"
          ],
          "onDelete": "cascade",
          "onUpdate": "no action"
        },
        "orders_book_listing_id_book_listings_id_fk": {
          "name": "orders_book_listing_id_book_listings_id_fk",
          "tableFrom": "orders",
          "tableTo": "book_listings",
          "columnsFrom": [
            "book_listing_id"
          ],
          "columnsTo": [
            "id"
          ],
          "onDelete": "cascade",
          "onUpdate": "no action"
        },
        "orders_escrow_id_escrow_accounts_id_fk": {
          "name": "orders_escrow_id_escrow_accounts_id_fk",
          "tableFrom": "orders",
          "tableTo": "escrow_accounts",
          "columnsFrom": [
            "escrow_id"
          ],
          "columnsTo": [
            "id"
          ],
          "onDelete": "no action",
          "onUpdate": "no action"
        }
      },
      "compositePrimaryKeys": {
        "orders_id": {
          "name": "orders_id",
          "columns": [
            "id"
          ]
        }
      },
      "uniqueConstraints": {
        "orders_order_number_unique": {
          "name": "orders_order_number_unique",
          "columns": [
            "order_number"
          ]
        }
      },
      "checkConstraint": {}
    },
    "otp_codes": {
      "name": "otp_codes",
      "columns": {
        "id": {
          "name": "id",
          "type": "varchar(36)",
          "primaryKey": false,
          "notNull": true,
          "autoincrement": false
        },
        "phone_number": {
          "name": "phone_number",
          "type": "varchar(20)",
          "primaryKey": false,
          "notNull": true,
          "autoincrement": false
        },
        "code": {
          "name": "code",
          "type": "varchar(6)",
          "primaryKey": false,
          "notNull": true,
          "autoincrement": false
        },
        "expires_at": {
          "name": "expires_at",
          "type": "timestamp",
          "primaryKey": false,
          "notNull": true,
          "autoincrement": false
        },
        "verified": {
          "name": "verified",
          "type": "boolean",
          "primaryKey": false,
          "notNull": true,
          "autoincrement": false,
          "default": false
        },
        "created_at": {
          "name": "created_at",
          "type": "timestamp",
          "primaryKey": false,
          "notNull": true,
          "autoincrement": false,
          "default": "(now())"
        }
      },
      "indexes": {
        "idx_otp_phone_code": {
          "name": "idx_otp_phone_code",
          "columns": [
            "phone_number",
            "code"
          ],
          "isUnique": false
        },
        "idx_otp_expires": {
          "name": "idx_otp_expires",
          "columns": [
            "expires_at"
          ],
          "isUnique": false
        }
      },
      "foreignKeys": {},
      "compositePrimaryKeys": {
        "otp_codes_id": {
          "name": "otp_codes_id",
          "columns": [
            "id"
          ]
        }
      },
      "uniqueConstraints": {},
      "checkConstraint": {}
    },
    "paystack_recipients": {
      "name": "paystack_recipients",
      "columns": {
        "id": {
          "name": "id",
          "type": "int",
          "primaryKey": false,
          "notNull": true,
          "autoincrement": true
        },
        "user_id": {
          "name": "user_id",
          "type": "varchar(36)",
          "primaryKey": false,
          "notNull": true,
          "autoincrement": false
        },
        "recipient_code": {
          "name": "recipient_code",
          "type": "varchar(255)",
          "primaryKey": false,
          "notNull": true,
          "autoincrement": false
        },
        "type": {
          "name": "type",
          "type": "varchar(20)",
          "primaryKey": false,
          "notNull": true,
          "autoincrement": false
        },
        "name": {
          "name": "name",
          "type": "varchar(255)",
          "primaryKey": false,
          "notNull": true,
          "autoincrement": false
        },
        "account_number": {
          "name": "account_number",
          "type": "varchar(50)",
          "primaryKey": false,
          "notNull": true,
          "autoincrement": false
        },
        "bank_code": {
          "name": "bank_code",
          "type": "varchar(50)",
          "primaryKey": false,
          "notNull": true,
          "autoincrement": false
        },
        "bank_name": {
          "name": "bank_name",
          "type": "varchar(255)",
          "primaryKey": false,
          "notNull": false,
          "autoincrement": false
        },
        "currency": {
          "name": "currency",
          "type": "varchar(10)",
          "primaryKey": false,
          "notNull": true,
          "autoincrement": false,
          "default": "'KES'"
        },
        "active": {
          "name": "active",
          "type": "boolean",
          "primaryKey": false,
          "notNull": true,
          "autoincrement": false,
          "default": true
        },
        "paystack_data": {
          "name": "paystack_data",
          "type": "text",
          "primaryKey": false,
          "notNull": false,
          "autoincrement": false
        },
        "created_at": {
          "name": "created_at",
          "type": "timestamp",
          "primaryKey": false,
          "notNull": true,
          "autoincrement": false,
          "default": "(now())"
        },
        "updated_at": {
          "name": "updated_at",
          "type": "timestamp",
          "primaryKey": false,
          "notNull": true,
          "autoincrement": false,
          "default": "(now())"
        }
      },
      "indexes": {},
      "foreignKeys": {
        "paystack_recipients_user_id_users_id_fk": {
          "name": "paystack_recipients_user_id_users_id_fk",
          "tableFrom": "paystack_recipients",
          "tableTo": "users",
          "columnsFrom": [
            "user_id"
          ],
          "columnsTo": [
            "id"
          ],
          "onDelete": "cascade",
          "onUpdate": "no action"
        }
      },
      "compositePrimaryKeys": {
        "paystack_recipients_id": {
          "name": "paystack_recipients_id",
          "columns": [
            "id"
          ]
        }
      },
      "uniqueConstraints": {
        "paystack_recipients_recipient_code_unique": {
          "name": "paystack_recipients_recipient_code_unique",
          "columns": [
            "recipient_code"
          ]
        }
      },
      "checkConstraint": {}
    },
    "publishers": {
      "name": "publishers",
      "columns": {
        "id": {
          "name": "id",
          "type": "int",
          "primaryKey": false,
          "notNull": true,
          "autoincrement": true
        },
        "name": {
          "name": "name",
          "type": "varchar(255)",
          "primaryKey": false,
          "notNull": true,
          "autoincrement": false
        },
        "country": {
          "name": "country",
          "type": "varchar(100)",
          "primaryKey": false,
          "notNull": false,
          "autoincrement": false
        },
        "website_url": {
          "name": "website_url",
          "type": "text",
          "primaryKey": false,
          "notNull": false,
          "autoincrement": false
        }
      },
      "indexes": {},
      "foreignKeys": {},
      "compositePrimaryKeys": {
        "publishers_id": {
          "name": "publishers_id",
          "columns": [
            "id"
          ]
        }
      },
      "uniqueConstraints": {
        "publishers_name_unique": {
          "name": "publishers_name_unique",
          "columns": [
            "name"
          ]
        }
      },
      "checkConstraint": {}
    },
    "schools": {
      "name": "schools",
      "columns": {
        "id": {
          "name": "id",
          "type": "varchar(36)",
          "primaryKey": false,
          "notNull": true,
          "autoincrement": false
        },
        "name": {
          "name": "name",
          "type": "text",
          "primaryKey": false,
          "notNull": true,
          "autoincrement": false
        },
        "location": {
          "name": "location",
          "type": "text",
          "primaryKey": false,
          "notNull": false,
          "autoincrement": false
        },
        "latitude": {
          "name": "latitude",
          "type": "decimal(10,7)",
          "primaryKey": false,
          "notNull": false,
          "autoincrement": false
        },
        "longitude": {
          "name": "longitude",
          "type": "decimal(10,7)",
          "primaryKey": false,
          "notNull": false,
          "autoincrement": false
        },
        "created_at": {
          "name": "created_at",
          "type": "timestamp",
          "primaryKey": false,
          "notNull": true,
          "autoincrement": false,
          "default": "(now())"
        }
      },
      "indexes": {
        "idx_schools_name": {
          "name": "idx_schools_name",
          "columns": [
            "name"
          ],
          "isUnique": false
        }
      },
      "foreignKeys": {},
      "compositePrimaryKeys": {
        "schools_id": {
          "name": "schools_id",
          "columns": [
            "id"
          ]
        }
      },
      "uniqueConstraints": {},
      "checkConstraint": {}
    },
    "subjects": {
      "name": "subjects",
      "columns": {
        "id": {
          "name": "id",
          "type": "int",
          "primaryKey": false,
          "notNull": true,
          "autoincrement": true
        },
        "name": {
          "name": "name",
          "type": "varchar(100)",
          "primaryKey": false,
          "notNull": true,
          "autoincrement": false
        },
        "description": {
          "name": "description",
          "type": "text",
          "primaryKey": false,
          "notNull": false,
          "autoincrement": false
        },
        "icon_url": {
          "name": "icon_url",
          "type": "text",
          "primaryKey": false,
          "notNull": false,
          "autoincrement": false
        },
        "sort_order": {
          "name": "sort_order",
          "type": "int",
          "primaryKey": false,
          "notNull": false,
          "autoincrement": false,
          "default": 0
        }
      },
      "indexes": {},
      "foreignKeys": {},
      "compositePrimaryKeys": {
        "subjects_id": {
          "name": "subjects_id",
          "columns": [
            "id"
          ]
        }
      },
      "uniqueConstraints": {
        "subjects_name_unique": {
          "name": "subjects_name_unique",
          "columns": [
            "name"
          ]
        }
      },
      "checkConstraint": {}
    },
    "swap_requests": {
      "name": "swap_requests",
      "columns": {
        "id": {
          "name": "id",
          "type": "int",
          "primaryKey": false,
          "notNull": true,
          "autoincrement": true
        },
        "requester_id": {
          "name": "requester_id",
          "type": "varchar(36)",
          "primaryKey": false,
          "notNull": true,
          "autoincrement": false
        },
        "owner_id": {
          "name": "owner_id",
          "type": "varchar(36)",
          "primaryKey": false,
          "notNull": true,
          "autoincrement": false
        },
        "requested_listing_id": {
          "name": "requested_listing_id",
          "type": "int",
          "primaryKey": false,
          "notNull": true,
          "autoincrement": false
        },
        "offered_book_title": {
          "name": "offered_book_title",
          "type": "varchar(500)",
          "primaryKey": false,
          "notNull": true,
          "autoincrement": false
        },
        "offered_book_author": {
          "name": "offered_book_author",
          "type": "varchar(255)",
          "primaryKey": false,
          "notNull": false,
          "autoincrement": false
        },
        "offered_book_condition": {
          "name": "offered_book_condition",
          "type": "varchar(20)",
          "primaryKey": false,
          "notNull": true,
          "autoincrement": false
        },
        "offered_book_description": {
          "name": "offered_book_description",
          "type": "text",
          "primaryKey": false,
          "notNull": false,
          "autoincrement": false
        },
        "offered_book_photo_url": {
          "name": "offered_book_photo_url",
          "type": "text",
          "primaryKey": false,
          "notNull": false,
          "autoincrement": false
        },
        "message": {
          "name": "message",
          "type": "text",
          "primaryKey": false,
          "notNull": false,
          "autoincrement": false
        },
        "status": {
          "name": "status",
          "type": "varchar(20)",
          "primaryKey": false,
          "notNull": true,
          "autoincrement": false,
          "default": "'pending'"
        },
        "commitment_fee": {
          "name": "commitment_fee",
          "type": "decimal(10,2)",
          "primaryKey": false,
          "notNull": false,
          "autoincrement": false,
          "default": "'0.00'"
        },
        "requester_paid": {
          "name": "requester_paid",
          "type": "boolean",
          "primaryKey": false,
          "notNull": false,
          "autoincrement": false,
          "default": false
        },
        "owner_paid": {
          "name": "owner_paid",
          "type": "boolean",
          "primaryKey": false,
          "notNull": false,
          "autoincrement": false,
          "default": false
        },
        "escrow_id": {
          "name": "escrow_id",
          "type": "int",
          "primaryKey": false,
          "notNull": false,
          "autoincrement": false
        },
        "meetup_location": {
          "name": "meetup_location",
          "type": "text",
          "primaryKey": false,
          "notNull": false,
          "autoincrement": false
        },
        "meetup_time": {
          "name": "meetup_time",
          "type": "timestamp",
          "primaryKey": false,
          "notNull": false,
          "autoincrement": false
        },
        "delivery_method": {
          "name": "delivery_method",
          "type": "varchar(50)",
          "primaryKey": false,
          "notNull": false,
          "autoincrement": false,
          "default": "'meetup'"
        },
        "requester_confirmed": {
          "name": "requester_confirmed",
          "type": "boolean",
          "primaryKey": false,
          "notNull": false,
          "autoincrement": false,
          "default": false
        },
        "owner_confirmed": {
          "name": "owner_confirmed",
          "type": "boolean",
          "primaryKey": false,
          "notNull": false,
          "autoincrement": false,
          "default": false
        },
        "created_at": {
          "name": "created_at",
          "type": "timestamp",
          "primaryKey": false,
          "notNull": true,
          "autoincrement": false,
          "default": "(now())"
        },
        "updated_at": {
          "name": "updated_at",
          "type": "timestamp",
          "primaryKey": false,
          "notNull": true,
          "autoincrement": false,
          "default": "(now())"
        },
        "accepted_at": {
          "name": "accepted_at",
          "type": "timestamp",
          "primaryKey": false,
          "notNull": false,
          "autoincrement": false
        },
        "completed_at": {
          "name": "completed_at",
          "type": "timestamp",
          "primaryKey": false,
          "notNull": false,
          "autoincrement": false
        },
        "cancelled_at": {
          "name": "cancelled_at",
          "type": "timestamp",
          "primaryKey": false,
          "notNull": false,
          "autoincrement": false
        }
      },
      "indexes": {
        "idx_swap_requests_requester": {
          "name": "idx_swap_requests_requester",
          "columns": [
            "requester_id"
          ],
          "isUnique": false
        },
        "idx_swap_requests_owner": {
          "name": "idx_swap_requests_owner",
          "columns": [
            "owner_id"
          ],
          "isUnique": false
        },
        "idx_swap_requests_listing": {
          "name": "idx_swap_requests_listing",
          "columns": [
            "requested_listing_id"
          ],
          "isUnique": false
        },
        "idx_swap_requests_status": {
          "name": "idx_swap_requests_status",
          "columns": [
            "status"
          ],
          "isUnique": false
        }
      },
      "foreignKeys": {
        "swap_requests_requester_id_users_id_fk": {
          "name": "swap_requests_requester_id_users_id_fk",
          "tableFrom": "swap_requests",
          "tableTo": "users",
          "columnsFrom": [
            "requester_id"
          ],
          "columnsTo": [
            "id"
          ],
          "onDelete": "cascade",
          "onUpdate": "no action"
        },
        "swap_requests_owner_id_users_id_fk": {
          "name": "swap_requests_owner_id_users_id_fk",
          "tableFrom": "swap_requests",
          "tableTo": "users",
          "columnsFrom": [
            "owner_id"
          ],
          "columnsTo": [
            "id"
          ],
          "onDelete": "cascade",
          "onUpdate": "no action"
        },
        "swap_requests_requested_listing_id_book_listings_id_fk": {
          "name": "swap_requests_requested_listing_id_book_listings_id_fk",
          "tableFrom": "swap_requests",
          "tableTo": "book_listings",
          "columnsFrom": [
            "requested_listing_id"
          ],
          "columnsTo": [
            "id"
          ],
          "onDelete": "cascade",
          "onUpdate": "no action"
        },
        "swap_requests_escrow_id_escrow_accounts_id_fk": {
          "name": "swap_requests_escrow_id_escrow_accounts_id_fk",
          "tableFrom": "swap_requests",
          "tableTo": "escrow_accounts",
          "columnsFrom": [
            "escrow_id"
          ],
          "columnsTo": [
            "id"
          ],
          "onDelete": "no action",
          "onUpdate": "no action"
        }
      },
      "compositePrimaryKeys": {
        "swap_requests_id": {
          "name": "swap_requests_id",
          "columns": [
            "id"
          ]
        }
      },
      "uniqueConstraints": {},
      "checkConstraint": {}
    },
    "transactions": {
      "name": "transactions",
      "columns": {
        "id": {
          "name": "id",
          "type": "int",
          "primaryKey": false,
          "notNull": true,
          "autoincrement": true
        },
        "user_id": {
          "name": "user_id",
          "type": "varchar(36)",
          "primaryKey": false,
          "notNull": true,
          "autoincrement": false
        },
        "type": {
          "name": "type",
          "type": "varchar(20)",
          "primaryKey": false,
          "notNull": true,
          "autoincrement": false
        },
        "status": {
          "name": "status",
          "type": "varchar(20)",
          "primaryKey": false,
          "notNull": true,
          "autoincrement": false,
          "default": "'pending'"
        },
        "amount": {
          "name": "amount",
          "type": "decimal(10,2)",
          "primaryKey": false,
          "notNull": true,
          "autoincrement": false
        },
        "currency": {
          "name": "currency",
          "type": "varchar(10)",
          "primaryKey": false,
          "notNull": true,
          "autoincrement": false,
          "default": "'KES'"
        },
        "payment_method": {
          "name": "payment_method",
          "type": "varchar(50)",
          "primaryKey": false,
          "notNull": false,
          "autoincrement": false
        },
        "payment_reference": {
          "name": "payment_reference",
          "type": "varchar(255)",
          "primaryKey": false,
          "notNull": false,
          "autoincrement": false
        },
        "book_listing_id": {
          "name": "book_listing_id",
          "type": "int",
          "primaryKey": false,
          "notNull": false,
          "autoincrement": false
        },
        "escrow_id": {
          "name": "escrow_id",
          "type": "int",
          "primaryKey": false,
          "notNull": false,
          "autoincrement": false
        },
        "description": {
          "name": "description",
          "type": "text",
          "primaryKey": false,
          "notNull": false,
          "autoincrement": false
        },
        "metadata": {
          "name": "metadata",
          "type": "text",
          "primaryKey": false,
          "notNull": false,
          "autoincrement": false
        },
        "created_at": {
          "name": "created_at",
          "type": "timestamp",
          "primaryKey": false,
          "notNull": true,
          "autoincrement": false,
          "default": "(now())"
        },
        "completed_at": {
          "name": "completed_at",
          "type": "timestamp",
          "primaryKey": false,
          "notNull": false,
          "autoincrement": false
        }
      },
      "indexes": {},
      "foreignKeys": {
        "transactions_user_id_users_id_fk": {
          "name": "transactions_user_id_users_id_fk",
          "tableFrom": "transactions",
          "tableTo": "users",
          "columnsFrom": [
            "user_id"
          ],
          "columnsTo": [
            "id"
          ],
          "onDelete": "cascade",
          "onUpdate": "no action"
        },
        "transactions_book_listing_id_book_listings_id_fk": {
          "name": "transactions_book_listing_id_book_listings_id_fk",
          "tableFrom": "transactions",
          "tableTo": "book_listings",
          "columnsFrom": [
            "book_listing_id"
          ],
          "columnsTo": [
            "id"
          ],
          "onDelete": "set null",
          "onUpdate": "no action"
        }
      },
      "compositePrimaryKeys": {
        "transactions_id": {
          "name": "transactions_id",
          "columns": [
            "id"
          ]
        }
      },
      "uniqueConstraints": {},
      "checkConstraint": {}
    },
    "user_preferences": {
      "name": "user_preferences",
      "columns": {
        "id": {
          "name": "id",
          "type": "int",
          "primaryKey": false,
          "notNull": true,
          "autoincrement": true
        },
        "user_id": {
          "name": "user_id",
          "type": "varchar(36)",
          "primaryKey": false,
          "notNull": true,
          "autoincrement": false
        },
        "email_notifications": {
          "name": "email_notifications",
          "type": "boolean",
          "primaryKey": false,
          "notNull": true,
          "autoincrement": false,
          "default": true
        },
        "push_notifications": {
          "name": "push_notifications",
          "type": "boolean",
          "primaryKey": false,
          "notNull": true,
          "autoincrement": false,
          "default": true
        },
        "sms_notifications": {
          "name": "sms_notifications",
          "type": "boolean",
          "primaryKey": false,
          "notNull": true,
          "autoincrement": false,
          "default": false
        },
        "notify_on_new_messages": {
          "name": "notify_on_new_messages",
          "type": "boolean",
          "primaryKey": false,
          "notNull": true,
          "autoincrement": false,
          "default": true
        },
        "notify_on_book_sold": {
          "name": "notify_on_book_sold",
          "type": "boolean",
          "primaryKey": false,
          "notNull": true,
          "autoincrement": false,
          "default": true
        },
        "notify_on_price_drops": {
          "name": "notify_on_price_drops",
          "type": "boolean",
          "primaryKey": false,
          "notNull": true,
          "autoincrement": false,
          "default": true
        },
        "notify_on_new_listings": {
          "name": "notify_on_new_listings",
          "type": "boolean",
          "primaryKey": false,
          "notNull": true,
          "autoincrement": false,
          "default": false
        },
        "preferred_payment_method": {
          "name": "preferred_payment_method",
          "type": "varchar(50)",
          "primaryKey": false,
          "notNull": false,
          "autoincrement": false,
          "default": "'mpesa'"
        },
        "mpesa_phone_number": {
          "name": "mpesa_phone_number",
          "type": "varchar(20)",
          "primaryKey": false,
          "notNull": false,
          "autoincrement": false
        },
        "bank_name": {
          "name": "bank_name",
          "type": "varchar(100)",
          "primaryKey": false,
          "notNull": false,
          "autoincrement": false
        },
        "bank_account_number": {
          "name": "bank_account_number",
          "type": "varchar(50)",
          "primaryKey": false,
          "notNull": false,
          "autoincrement": false
        },
        "bank_account_name": {
          "name": "bank_account_name",
          "type": "varchar(255)",
          "primaryKey": false,
          "notNull": false,
          "autoincrement": false
        },
        "bank_branch": {
          "name": "bank_branch",
          "type": "varchar(100)",
          "primaryKey": false,
          "notNull": false,
          "autoincrement": false
        },
        "paypal_email": {
          "name": "paypal_email",
          "type": "varchar(255)",
          "primaryKey": false,
          "notNull": false,
          "autoincrement": false
        },
        "currency": {
          "name": "currency",
          "type": "varchar(10)",
          "primaryKey": false,
          "notNull": false,
          "autoincrement": false,
          "default": "'KES'"
        },
        "language": {
          "name": "language",
          "type": "varchar(10)",
          "primaryKey": false,
          "notNull": false,
          "autoincrement": false,
          "default": "'en'"
        },
        "created_at": {
          "name": "created_at",
          "type": "timestamp",
          "primaryKey": false,
          "notNull": true,
          "autoincrement": false,
          "default": "(now())"
        },
        "updated_at": {
          "name": "updated_at",
          "type": "timestamp",
          "primaryKey": false,
          "notNull": true,
          "autoincrement": false,
          "default": "(now())"
        }
      },
      "indexes": {},
      "foreignKeys": {
        "user_preferences_user_id_users_id_fk": {
          "name": "user_preferences_user_id_users_id_fk",
          "tableFrom": "user_preferences",
          "tableTo": "users",
          "columnsFrom": [
            "user_id"
          ],
          "columnsTo": [
            "id"
          ],
          "onDelete": "cascade",
          "onUpdate": "no action"
        }
      },
      "compositePrimaryKeys": {
        "user_preferences_id": {
          "name": "user_preferences_id",
          "columns": [
            "id"
          ]
        }
      },
      "uniqueConstraints": {
        "user_preferences_user_id_unique": {
          "name": "user_preferences_user_id_unique",
          "columns": [
            "user_id"
          ]
        }
      },
      "checkConstraint": {}
    },
    "users": {
      "name": "users",
      "columns": {
        "id": {
          "name": "id",
          "type": "varchar(36)",
          "primaryKey": false,
          "notNull": true,
          "autoincrement": false
        },
        "phone_number": {
          "name": "phone_number",
          "type": "varchar(20)",
          "primaryKey": false,
          "notNull": true,
          "autoincrement": false
        },
        "full_name": {
          "name": "full_name",
          "type": "text",
          "primaryKey": false,
          "notNull": false,
          "autoincrement": false
        },
        "email": {
          "name": "email",
          "type": "varchar(255)",
          "primaryKey": false,
          "notNull": false,
          "autoincrement": false
        },
        "profile_picture_url": {
          "name": "profile_picture_url",
          "type": "text",
          "primaryKey": false,
          "notNull": false,
          "autoincrement": false
        },
        "role": {
          "name": "role",
          "type": "varchar(20)",
          "primaryKey": false,
          "notNull": true,
          "autoincrement": false,
          "default": "'PARENT'"
        },
        "school_id": {
          "name": "school_id",
          "type": "varchar(36)",
          "primaryKey": false,
          "notNull": false,
          "autoincrement": false
        },
        "school_name": {
          "name": "school_name",
          "type": "text",
          "primaryKey": false,
          "notNull": false,
          "autoincrement": false
        },
        "latitude": {
          "name": "latitude",
          "type": "decimal(10,7)",
          "primaryKey": false,
          "notNull": false,
          "autoincrement": false
        },
        "longitude": {
          "name": "longitude",
          "type": "decimal(10,7)",
          "primaryKey": false,
          "notNull": false,
          "autoincrement": false
        },
        "child_grade": {
          "name": "child_grade",
          "type": "int",
          "primaryKey": false,
          "notNull": false,
          "autoincrement": false
        },
        "onboarding_completed": {
          "name": "onboarding_completed",
          "type": "boolean",
          "primaryKey": false,
          "notNull": true,
          "autoincrement": false,
          "default": false
        },
        "wallet_balance": {
          "name": "wallet_balance",
          "type": "decimal(10,2)",
          "primaryKey": false,
          "notNull": true,
          "autoincrement": false,
          "default": "'0.00'"
        },
        "created_at": {
          "name": "created_at",
          "type": "timestamp",
          "primaryKey": false,
          "notNull": true,
          "autoincrement": false,
          "default": "(now())"
        },
        "updated_at": {
          "name": "updated_at",
          "type": "timestamp",
          "primaryKey": false,
          "notNull": true,
          "autoincrement": false,
          "default": "(now())"
        }
      },
      "indexes": {
        "idx_users_phone": {
          "name": "idx_users_phone",
          "columns": [
            "phone_number"
          ],
          "isUnique": false
        },
        "idx_users_school": {
          "name": "idx_users_school",
          "columns": [
            "school_id"
          ],
          "isUnique": false
        }
      },
      "foreignKeys": {},
      "compositePrimaryKeys": {
        "users_id": {
          "name": "users_id",
          "columns": [
            "id"
          ]
        }
      },
      "uniqueConstraints": {
        "users_phone_number_unique": {
          "name": "users_phone_number_unique",
          "columns": [
            "phone_number"
          ]
        }
      },
      "checkConstraint": {}
    },
    "wallet_transactions": {
      "name": "wallet_transactions",
      "columns": {
        "id": {
          "name": "id",
          "type": "int",
          "primaryKey": false,
          "notNull": true,
          "autoincrement": true
        },
        "user_id": {
          "name": "user_id",
          "type": "varchar(36)",
          "primaryKey": false,
          "notNull": true,
          "autoincrement": false
        },
        "type": {
          "name": "type",
          "type": "varchar(10)",
          "primaryKey": false,
          "notNull": true,
          "autoincrement": false
        },
        "amount": {
          "name": "amount",
          "type": "decimal(10,2)",
          "primaryKey": false,
          "notNull": true,
          "autoincrement": false
        },
        "balance_after": {
          "name": "balance_after",
          "type": "decimal(10,2)",
          "primaryKey": false,
          "notNull": true,
          "autoincrement": false
        },
        "transaction_id": {
          "name": "transaction_id",
          "type": "int",
          "primaryKey": false,
          "notNull": true,
          "autoincrement": false
        },
        "description": {
          "name": "description",
          "type": "text",
          "primaryKey": false,
          "notNull": true,
          "autoincrement": false
        },
        "created_at": {
          "name": "created_at",
          "type": "timestamp",
          "primaryKey": false,
          "notNull": true,
          "autoincrement": false,
          "default": "(now())"
        }
      },
      "indexes": {},
      "foreignKeys": {
        "wallet_transactions_user_id_users_id_fk": {
          "name": "wallet_transactions_user_id_users_id_fk",
          "tableFrom": "wallet_transactions",
          "tableTo": "users",
          "columnsFrom": [
            "user_id"
          ],
          "columnsTo": [
            "id"
          ],
          "onDelete": "cascade",
          "onUpdate": "no action"
        },
        "wallet_transactions_transaction_id_transactions_id_fk": {
          "name": "wallet_transactions_transaction_id_transactions_id_fk",
          "tableFrom": "wallet_transactions",
          "tableTo": "transactions",
          "columnsFrom": [
            "transaction_id"
          ],
          "columnsTo": [
            "id"
          ],
          "onDelete": "cascade",
          "onUpdate": "no action"
        }
      },
      "compositePrimaryKeys": {
        "wallet_transactions_id": {
          "name": "wallet_transactions_id",
          "columns": [
            "id"
          ]
        }
      },
      "uniqueConstraints": {},
      "checkConstraint": {}
    }
  },
  "views": {},
  "_meta": {
    "schemas": {},
    "tables": {},
    "columns": {}
  },
  "internal": {
    "tables": {},
    "indexes": {}
  }
}